payparts/__init__.py
payparts/adapter.py
payparts/admin.py
payparts/apps.py
payparts/client.py
payparts/consts.py
payparts/exceptions.py
payparts/forms.py
payparts/models.py
payparts/payparts.py
payparts/settings.py
payparts/signals.py
payparts/templates.py
payparts/tests.py
payparts/urls.py
payparts/use_cases.py
payparts/views.py
payparts/locale/en/LC_MESSAGES/django.po
payparts/locale/ru/LC_MESSAGES/django.po
payparts/locale/uk/LC_MESSAGES/django.po
payparts/migrations/0001_initial.py
payparts/migrations/0002_auto_20190528_0813.py
payparts/migrations/__init__.py
django_ok_payparts-0.4.dist-info/LICENSE
django_ok_payparts-0.4.dist-info/METADATA
django_ok_payparts-0.4.dist-info/WHEEL
django_ok_payparts-0.4.dist-info/top_level.txt
django_ok_payparts-0.4.dist-info/RECORD
