Metadata-Version: 2.1
Name: django-ok-payparts
Version: 0.4
Summary: Django integration for API "https://bw.gitbooks.io/api-oc/content/pay.html".
Home-page: https://github.com/LowerDeez/ok-payparts
Author: Oleg Kleschunov
Author-email: igorkleschunov@gmail.com
License: MIT
Keywords: python,payparts,django
Platform: UNKNOWN
Classifier: Environment :: Web Environment
Classifier: Development Status :: 4 - Beta
Classifier: Operating System :: OS Independent
Classifier: Framework :: Django :: 2.0
Classifier: Framework :: Django :: 2.1
Classifier: Framework :: Django :: 2.2
Classifier: Intended Audience :: Developers
Classifier: Programming Language :: Python :: 3.6
Classifier: Programming Language :: Python :: 3.7
Requires-Dist: Django (>=2.0)
Requires-Dist: trafaret (==1.2.0)
